{
  "key": "3fefe462f2f03e3a302f01cb7f081b49",
  "value": [
    {
      "rule": "C003",
      "line": 12,
      "column": 0,
      "severity": "warning",
      "message": "Variable name 'name' is generic and does not clearly indicate its purpose in the logger context.",
      "suggestion": "Rename 'name' to 'loggerName' for clarity.",
      "codeSnippet": "const createLogger = (name:string) => ({",
      "filePath": "/home/mhugo/code/zenflow/packages/services/telemetry/src/telemetry-event-driven.ts",
      "category": "code_quality",
      "categoryName": "Code Quality",
      "analysisMode": "medium",
      "confidence": 0.85
    },
    {
      "rule": "C003",
      "line": 96,
      "column": 0,
      "severity": "warning",
      "message": "Variable name 'data' is generic and used in multiple event handlers, reducing clarity.",
      "suggestion": "Rename 'data' to a more descriptive name such as 'eventData' or specific to the event type.",
      "codeSnippet": "requestId:string;",
      "filePath": "/home/mhugo/code/zenflow/packages/services/telemetry/src/telemetry-event-driven.ts",
      "category": "code_quality",
      "categoryName": "Code Quality",
      "analysisMode": "medium",
      "confidence": 0.85
    },
    {
      "rule": "C006",
      "line": 12,
      "column": 0,
      "severity": "warning",
      "message": "Function name 'createLogger' is a noun phrase; should be a verb or verb-noun combination.",
      "suggestion": "Rename to 'initializeLogger' or 'buildLogger'.",
      "codeSnippet": "const createLogger = (name:string) => ({",
      "filePath": "/home/mhugo/code/zenflow/packages/services/telemetry/src/telemetry-event-driven.ts",
      "category": "code_quality",
      "categoryName": "Code Quality",
      "analysisMode": "medium",
      "confidence": 0.85
    },
    {
      "rule": "C029",
      "line": 61,
      "column": 0,
      "severity": "warning",
      "message": "Catch block in 'emitEvent' only logs error message, not stack trace or context.",
      "suggestion": "Log both error message and stack trace, and include event context information.",
      "codeSnippet": "name:string;",
      "filePath": "/home/mhugo/code/zenflow/packages/services/telemetry/src/telemetry-event-driven.ts",
      "category": "code_quality",
      "categoryName": "Code Quality",
      "analysisMode": "medium",
      "confidence": 0.85
    }
  ],
  "timestamp": 1756490504873,
  "version": "1.0.0",
  "fileHash": ""
}
